README.rst
setup.py
brow/__init__.py
brow/compat.py
brow/core.py
brow/environ.py
brow/exception.py
brow.egg-info/PKG-INFO
brow.egg-info/SOURCES.txt
brow.egg-info/dependency_links.txt
brow.egg-info/requires.txt
brow.egg-info/top_level.txt
brow/interface/__init__.py
brow/interface/base.py
brow/interface/selenium.py
brow/interface/simple.py
tests/__init__.py
tests/core_test.py
tests/interface_test.py