Metadata-Version: 1.1
Name: brow
Version: 0.0.2
Summary: Control a web browser using python
Home-page: http://github.com/jaymon/brow
Author: Jay Marcyes
Author-email: jay@marcyes.com
License: MIT
Platform: UNKNOWN
Classifier: Development Status :: 4 - Beta
Classifier: Environment :: Web Environment
Classifier: Intended Audience :: Developers
Classifier: License :: OSI Approved :: MIT License
Classifier: Operating System :: OS Independent
Classifier: Topic :: Software Development :: Libraries
Classifier: Topic :: Utilities
Classifier: Programming Language :: Python :: 2.7
